MANIFEST.in
setup.py
Docta.egg-info/PKG-INFO
Docta.egg-info/SOURCES.txt
Docta.egg-info/dependency_links.txt
Docta.egg-info/entry_points.txt
Docta.egg-info/not-zip-safe
Docta.egg-info/requires.txt
Docta.egg-info/top_level.txt
docta/__init__.py
docta/chapters.py
docta/cli.py
docta/exceptions.py
docta/project.py
docta/render.py
docta/initial/README.md
docta/initial/default/config.yaml
docta/initial/default/index.md
docta/initial/default/install.md
docta/initial/default/quickstart.md
docta/initial/default/_resources/favicon.png
docta/initial/default/_resources/assets/css/bootstrap.min.css
docta/initial/default/_resources/assets/css/docta.css
docta/initial/default/_resources/assets/css/pygments.css
docta/initial/default/_resources/assets/fonts/glyphicons-halflings-regular.eot
docta/initial/default/_resources/assets/fonts/glyphicons-halflings-regular.svg
docta/initial/default/_resources/assets/fonts/glyphicons-halflings-regular.ttf
docta/initial/default/_resources/assets/fonts/glyphicons-halflings-regular.woff
docta/initial/default/_resources/assets/img/logo.png
docta/initial/default/_resources/assets/js/bootstrap.min.js
docta/initial/default/_templates/base.html
docta/initial/default/_templates/home.html
docta/initial/default/_templates/icon.html
docta/initial/default/_templates/index.html
docta/initial/default/_templates/page.html
docta/renderers/__init__.py
docta/renderers/base.py
docta/renderers/html.py
docta/utils/__init__.py
docta/utils/fs.py
docta/utils/json.py
docta/utils/log.py
docta/utils/md.py
docta/utils/meta.py
docta/utils/server.py
docta/utils/watcher.py