Metadata-Version: 1.1
Name: Docta
Version: 0.2.2
Summary: Docta is a new healing docs kit.
Home-page: https://github.com/05bit/docta
Author: Alexey Kinyov
Author-email: rudy@05bit.com
License: BSD
Platform: UNKNOWN
Classifier: Development Status :: 3 - Alpha
Classifier: Environment :: Console
Classifier: Environment :: Web Environment
Classifier: Intended Audience :: Developers
Classifier: License :: OSI Approved :: BSD License
Classifier: Operating System :: OS Independent
Classifier: Programming Language :: Python :: 2.7
Classifier: Programming Language :: Python :: 3
Classifier: Topic :: Internet
Classifier: Topic :: Text Processing
Classifier: Topic :: Utilities
